LICENSE
MANIFEST.in
README.md
setup.py
mambu_tests/__init__.py
mambu_tests/conftest.py
mambu_tests/constants.py
mambu_tests/helpers.py
mambu_tests/test_helpers.py
mambu_tests/test_sync.py
mambu_tests/multithreading/__init__.py
mambu_tests/multithreading/test_multithreaded_bookmark_daybyday_generator.py
mambu_tests/multithreading/test_multithreaded_bookmark_generator.py
mambu_tests/multithreading/test_multithreaded_offset_generator.py
mambu_tests/multithreading/test_requests_pool.py
mambu_tests/tap_generators/__init__.py
mambu_tests/tap_generators/test_activities_generator.py
mambu_tests/tap_generators/test_audit_trail_generator.py
mambu_tests/tap_generators/test_branches_generator.py
mambu_tests/tap_generators/test_centres_generator.py
mambu_tests/tap_generators/test_clients_generator.py
mambu_tests/tap_generators/test_communications_generator.py
mambu_tests/tap_generators/test_credit_arrangements_generator.py
mambu_tests/tap_generators/test_custom_field_sets_generator.py
mambu_tests/tap_generators/test_deposit_accounts_generator.py
mambu_tests/tap_generators/test_deposit_cards_generator.py
mambu_tests/tap_generators/test_deposit_products_generator.py
mambu_tests/tap_generators/test_deposit_transactions_generator.py
mambu_tests/tap_generators/test_generators.py
mambu_tests/tap_generators/test_gl_accounts_generator.py
mambu_tests/tap_generators/test_gl_journal_entries_generator.py
mambu_tests/tap_generators/test_groups_generator.py
mambu_tests/tap_generators/test_index_rate_sources_generator.py
mambu_tests/tap_generators/test_installments_generator.py
mambu_tests/tap_generators/test_interest_accrual_breakdown_generator.py
mambu_tests/tap_generators/test_loan_accounts_generators.py
mambu_tests/tap_generators/test_loan_products_generator.py
mambu_tests/tap_generators/test_loan_transactions_generator.py
mambu_tests/tap_generators/test_no_pagination_generators.py
mambu_tests/tap_generators/test_repayments_generator.py
mambu_tests/tap_generators/test_tasks_generator.py
tap_mambu.egg-info/PKG-INFO
tap_mambu.egg-info/SOURCES.txt
tap_mambu.egg-info/dependency_links.txt
tap_mambu.egg-info/entry_points.txt
tap_mambu.egg-info/requires.txt
tap_mambu.egg-info/top_level.txt
