Metadata-Version: 2.4
Name: tap-mambu
Version: 4.5.0
Summary: Singer.io tap for extracting data from the Mambu 2.0 API
Author: jeff.huth@bytecode.io
Classifier: Programming Language :: Python :: 3 :: Only
Requires-Python: >=3.9
License-File: LICENSE
Requires-Dist: backoff==1.10.0
Requires-Dist: requests==2.32.4
Requires-Dist: singer-python==5.13.2
Requires-Dist: pytz==2022.1
Provides-Extra: dev
Requires-Dist: ipdb; extra == "dev"
Requires-Dist: pylint==2.5.3; extra == "dev"
Requires-Dist: mock==5.0.2; extra == "dev"
Requires-Dist: pytest==6.2.4; extra == "dev"
Provides-Extra: mambu-tests
Requires-Dist: coverage==6.3.1; extra == "mambu-tests"
Requires-Dist: pylint==2.12.2; extra == "mambu-tests"
Requires-Dist: pytest==6.2.5; extra == "mambu-tests"
Requires-Dist: mock==4.0.3; extra == "mambu-tests"
Provides-Extra: mambu-performance
Requires-Dist: matplotlib==3.5.1; extra == "mambu-performance"
Dynamic: author
Dynamic: classifier
Dynamic: license-file
Dynamic: provides-extra
Dynamic: requires-dist
Dynamic: requires-python
Dynamic: summary
